sinp_organisms/__init__.py
sinp_organisms/admin.py
sinp_organisms/apps.py
sinp_organisms/fixtures/.gitkeep
sinp_organisms/fixtures/inpn_nomenclatures_organisms.json
sinp_organisms/fixtures/inpn_organisms.json
sinp_organisms/fixtures/test_data.json
sinp_organisms/locale/en/LC_MESSAGES/django.po
sinp_organisms/locale/fr/LC_MESSAGES/django.po
sinp_organisms/managers.py
sinp_organisms/migrations/0001_initial.py
sinp_organisms/migrations/0002_alter_organismmember_unique_together_and_more.py
sinp_organisms/migrations/__init__.py
sinp_organisms/mixins.py
sinp_organisms/models.py
sinp_organisms/serializers.py
sinp_organisms/tests.py
sinp_organisms/urls.py
sinp_organisms/validators.py
sinp_organisms/views.py
dj_sinp_organisms-1.4.2.dist-info/LICENSE
dj_sinp_organisms-1.4.2.dist-info/METADATA
dj_sinp_organisms-1.4.2.dist-info/WHEEL
dj_sinp_organisms-1.4.2.dist-info/RECORD
