Metadata-Version: 2.3
Name: dj_sinp_organisms
Version: 1.4.2
Summary: Django app to manage french SINP organisms standard
License: AGPLv3
Keywords: SINP,Nomenclatures,Django,France,dbChiroWeb
Author: dbChiro project
Requires-Python: >=3.9.0,<4.0
Classifier: License :: Other/Proprietary License
Classifier: Programming Language :: Python :: 3
Classifier: Programming Language :: Python :: 3.9
Classifier: Programming Language :: Python :: 3.10
Classifier: Programming Language :: Python :: 3.11
Classifier: Programming Language :: Python :: 3.12
Classifier: Programming Language :: Python :: 3.13
Requires-Dist: Django (>=3.2)
Requires-Dist: dj-sinp-nomenclatures (>=0.0.0)
Requires-Dist: djangorestframework (>=3,<4)
Project-URL: Documentation, https://dbchiro.github.io/DjangoSinpOrganisms/
Project-URL: Homepage, https://github.com/dbchiro/DjangoSinpOrganisms
Project-URL: Repository, https://github.com/dbchiro/DjangoSinpOrganisms
